booleam/__init__.py
booleam/boolem.py
boolem/__init__.py
boolem/boolem.py
boolem-0.0.5.dist-info/METADATA
boolem-0.0.5.dist-info/WHEEL
boolem-0.0.5.dist-info/top_level.txt
boolem-0.0.5.dist-info/RECORD
