Metadata-Version: 2.1
Name: boolem
Version: 0.0.5
Summary: Boolean matrix factorization on RNA expression data
Home-page: https://github.com/LifanLiang/EM_BMF
Author: Lifan Liang
Author-email: lil115@pitt.edu
License: UNKNOWN
Platform: UNKNOWN
Classifier: Programming Language :: Python :: 3
Classifier: License :: OSI Approved :: MIT License
Classifier: Operating System :: OS Independent
Requires-Python: >=3.4
